tilepie/__init__.py
tilepie/proj.py
tilepie/reader.py
tilepie-0.2.1.dist-info/DESCRIPTION.rst
tilepie-0.2.1.dist-info/METADATA
tilepie-0.2.1.dist-info/RECORD
tilepie-0.2.1.dist-info/WHEEL
tilepie-0.2.1.dist-info/metadata.json
tilepie-0.2.1.dist-info/top_level.txt
