Metadata-Version: 1.0
Name: tilepie
Version: 0.2.1
Summary: multiproc mbtile processing
Home-page: https://github.com/kamicut/tilepie
Author: Marc Farra
Author-email: marcfarra@gmail.com
License: MIT
Platform: UNKNOWN
